{"assets":{"967C3A773571D23026A48B4B5E612DC3":{"type":"texture","index":0,"assetRequest":{"type":"slide","state":"contents","slide":"none"},"url":{"native":"assets\/600BB890-F909-4457-9766-13FDEDE9C36B.pdf"},"width":1920,"height":1080},"E48ED7588EFC7DFFDB7472ABAFEAF0BE":{"type":"texture","index":1,"assetRequest":{"type":"slide","state":"contents","slide":"none"},"url":{"native":"assets\/600BB890-F909-4457-9766-13FDEDE9C36B.pdf"},"width":1920,"height":1080}},"events":[{"effects":[{"beginTime":0,"baseLayer":{"animations":[],"initialState":{"affineTransform":[1,0,0,1,0,0],"masksToBounds":false,"rotation":0,"scale":1,"position":{"pointX":960,"pointY":540},"width":1920,"sublayerTransform":[1,0,0,0,0,1,0,0,0,0,1,0,0,0,0,1],"contentsRect":{"y":0,"x":0,"width":1,"height":1},"opacity":1,"edgeAntialiasingMask":251658240,"height":1080,"hidden":false,"anchorPoint":{"pointX":0.5,"pointY":0.5}},"objectID":"0","layers":[{"animations":[],"initialState":{"affineTransform":[1,0,0,1,0,0],"masksToBounds":false,"rotation":0,"scale":1,"position":{"pointX":960,"pointY":540},"width":1920,"sublayerTransform":[1,0,0,0,0,1,0,0,0,0,1,-0.00035007912466775983,0,0,0,1],"contentsRect":{"y":0,"x":0,"width":1,"height":1},"opacity":1,"edgeAntialiasingMask":251658240,"height":1080,"hidden":false,"anchorPoint":{"pointX":0.5,"pointY":0.5}},"layers":[{"animations":[{"repeatCount":0,"timingControlPoint2y":0.9959721565246582,"removedOnCompletion":false,"from":{"pointX":2880,"pointY":540},"timingFunction":"custom","additive":false,"timeOffset":0,"autoreverses":false,"timingControlPoint1x":0.49705871939659119,"fillMode":"both","property":"position","duration":1,"beginTime":0,"timingControlPoint2x":0.49811732769012451,"timingControlPoint1y":0,"to":{"pointX":960,"pointY":540}}],"layers":[],"texturedRectangle":{"isBackgroundTexture":false,"singleTextureOpacity":1,"textureType":0,"textBaseline":0,"textXHeight":0,"isVerticalText":false},"initialState":{"affineTransform":[1,0,0,1,0,0],"masksToBounds":false,"rotation":0,"scale":1,"position":{"pointX":960,"pointY":540},"width":1920,"sublayerTransform":[1,0,0,0,0,1,0,0,0,0,1,0,0,0,0,1],"contentsRect":{"y":0,"x":0,"width":1,"height":1},"opacity":1,"edgeAntialiasingMask":0,"height":1080,"hidden":false,"anchorPoint":{"pointX":0.5,"pointY":0.5}},"texture":"E48ED7588EFC7DFFDB7472ABAFEAF0BE"},{"animations":[{"repeatCount":0,"timingControlPoint2y":0.9959721565246582,"removedOnCompletion":false,"from":{"pointX":960,"pointY":540},"timingFunction":"custom","additive":false,"timeOffset":0,"autoreverses":false,"timingControlPoint1x":0.49705871939659119,"fillMode":"both","property":"position","duration":1,"beginTime":0,"timingControlPoint2x":0.49811732769012451,"timingControlPoint1y":0,"to":{"pointX":-960,"pointY":540}}],"layers":[],"texturedRectangle":{"isBackgroundTexture":false,"singleTextureOpacity":1,"textureType":0,"textBaseline":0,"textXHeight":0,"isVerticalText":false},"initialState":{"affineTransform":[1,0,0,1,0,0],"masksToBounds":false,"rotation":0,"scale":1,"position":{"pointX":960,"pointY":540},"width":1920,"sublayerTransform":[1,0,0,0,0,1,0,0,0,0,1,0,0,0,0,1],"contentsRect":{"y":0,"x":0,"width":1,"height":1},"opacity":1,"edgeAntialiasingMask":0,"height":1080,"hidden":false,"anchorPoint":{"pointX":0.5,"pointY":0.5}},"texture":"967C3A773571D23026A48B4B5E612DC3"}]}]},"effects":[],"duration":1,"type":"transition","attributes":{"direction":12},"name":"apple:push","objectID":"0"}],"automaticPlay":false,"hyperlinks":[],"accessibility":[{"text":"2","targetRectangle":{"y":361.9444580078125,"x":1379,"width":29.950000000000045,"height":61}},{"text":"2","targetRectangle":{"y":366.47750854492188,"x":739,"width":29.950000000000045,"height":61}},{"text":"2","targetRectangle":{"y":901.9444580078125,"x":1378.9998779296875,"width":29.950000000000045,"height":61}},{"text":"1","targetRectangle":{"y":255.064453125,"x":1379,"width":20.25,"height":61}},{"text":"Reduced total cost of ownership","targetRectangle":{"y":585.44445753097534,"x":1379,"width":437.35499957755201,"height":153.99999737739563}},{"text":"Key  advantages of using basejmp","targetRectangle":{"y":144.19999694824219,"x":96.150902526855475,"width":445.42399999999998,"height":251.59999513626099}},{"text":"Deploy multiple applications as well as multiple instances of applications on the same platform.","targetRectangle":{"y":795.064453125,"x":797.61395263671875,"width":362.32199949306232,"height":94.5}},{"text":"Iteratively build and release features. No big-bang feature development and release.  Release in small packages rapidly.","targetRectangle":{"y":361.9444580078125,"x":1437.6138916015625,"width":393.47999948099255,"height":94.5}},{"text":"High productivity & flexibility","targetRectangle":{"y":61.055526256561279,"x":739.0001220703125,"width":441.62999954737734,"height":153.99999737739563}},{"text":"Reduce operational cost by eliminating the idling cost of multiple applications and instances.","targetRectangle":{"y":901.9444580078125,"x":797.61395263671875,"width":382.76999948099251,"height":94.5}},{"text":"Get more done with existing engineering resources. Eliminate need for scarcely  available\/expensive specialized talent.","targetRectangle":{"y":255.064453125,"x":797.61395263671875,"width":362.93399951720221,"height":94.5}},{"text":"Low code translates to low number of bugs and lower need of maintenance resources across the app lifecycle","targetRectangle":{"y":795.064453125,"x":1437.6138916015625,"width":386.36999949306255,"height":94.5}},{"text":"In case of bug, fix and verification are faster due to low complexity implementation. Lower chances of regression.","targetRectangle":{"y":901.9444580078125,"x":1437.6138916015625,"width":387.82799942064275,"height":94.5}},{"text":"Flexibility not sacrificed to achieve productivity. Anything possible with traditional development is possible with Basejmp.","targetRectangle":{"y":361.9444580078125,"x":797.61395263671875,"width":356.27399950513245,"height":126}},{"text":"Develop and release products and features faster. Adapt rapidly based on customer feedback. ","targetRectangle":{"y":255.064453125,"x":1437.6138916015625,"width":385.88399949306245,"height":94.5}},{"text":"Multi-tenant out of the box","targetRectangle":{"y":624.3333740234375,"x":739,"width":426.46499957755213,"height":104.49999868869781}},{"text":"2","targetRectangle":{"y":901.9444580078125,"x":739,"width":29.950000000000045,"height":61}},{"text":"Rapid and iterative development","targetRectangle":{"y":55.184447765350342,"x":1379,"width":381.59999966807663,"height":153.99999737739563}},{"text":"1","targetRectangle":{"y":795.064453125,"x":739,"width":20.25,"height":61}},{"text":"1","targetRectangle":{"y":259.59750366210938,"x":739,"width":20.25,"height":61}},{"text":"1","targetRectangle":{"y":795.064453125,"x":1378.9998779296875,"width":20.25,"height":61}}],"baseLayer":{"animations":[],"initialState":{"affineTransform":[1,0,0,1,0,0],"masksToBounds":false,"rotation":0,"scale":1,"position":{"pointX":960,"pointY":540},"width":1920,"sublayerTransform":[1,0,0,0,0,1,0,0,0,0,1,0,0,0,0,1],"contentsRect":{"y":0,"x":0,"width":1,"height":1},"opacity":1,"edgeAntialiasingMask":251658240,"height":1080,"hidden":false,"anchorPoint":{"pointX":0.5,"pointY":0.5}},"objectID":"0","layers":[{"animations":[],"initialState":{"affineTransform":[1,0,0,1,0,0],"masksToBounds":false,"rotation":0,"scale":1,"position":{"pointX":960,"pointY":540},"width":1920,"sublayerTransform":[1,0,0,0,0,1,0,0,0,0,1,-0.00035007912466775983,0,0,0,1],"contentsRect":{"y":0,"x":0,"width":1,"height":1},"opacity":1,"edgeAntialiasingMask":251658240,"height":1080,"hidden":false,"anchorPoint":{"pointX":0.5,"pointY":0.5}},"layers":[{"animations":[],"layers":[],"texturedRectangle":{"isBackgroundTexture":false,"singleTextureOpacity":1,"textureType":0,"textBaseline":0,"textXHeight":0,"isVerticalText":false},"initialState":{"affineTransform":[1,0,0,1,0,0],"masksToBounds":false,"rotation":0,"scale":1,"position":{"pointX":960,"pointY":540},"width":1920,"sublayerTransform":[1,0,0,0,0,1,0,0,0,0,1,0,0,0,0,1],"contentsRect":{"y":0,"x":0,"width":1,"height":1},"opacity":1,"edgeAntialiasingMask":0,"height":1080,"hidden":false,"anchorPoint":{"pointX":0.5,"pointY":0.5}},"texture":"967C3A773571D23026A48B4B5E612DC3"}]}]}}]}